{"Type": ["video"], "Url": ["https://www.cnn.com/videos/world/2020/01/26/connect-the-world-chief-palestinian-negotiator-saeb-erakat-trump-kushner-peace-plan-intl.cnn"], "Source": ["cnn"], "Location": false, "ByLine": false, "Writers": [[]], "FirstPublishDate": ["2020-01-26T17:24:50Z"], "LastModifiedDate": ["2020-01-26T17:24:50Z"], "Headline": ["Chief Palestinian Negotiator: Peace plan is 'the art of fraud'"], "Section": ["world"], "MappedSection": ["WORLD"], "Article_Body": ["Chief Palestinian Negotiator, Saeb Erakat, says there will be a unanimous Arab decision to reject President Trump's proposal. He says there has been no contact between the White House and the Palestinians since December, 2017.  "], "Language": false}