{"Type": ["video"], "Url": ["https://www.cnn.com/videos/tv/2019/12/13/the-seasons-new-christmas-music.cnn"], "Source": ["cnn"], "Location": false, "ByLine": false, "Writers": [[]], "FirstPublishDate": ["2019-12-13T23:01:21Z"], "LastModifiedDate": ["2019-12-13T23:01:21Z"], "Headline": ["The season's new Christmas music"], "Section": ["tv"], "MappedSection": [null], "Article_Body": ["From standards, to metal and pop, there are new Christmas songs out this year for every musical taste."], "Language": false}