{"Type": ["video"], "Url": ["https://www.cnn.com/videos/travel/2020/03/16/reasons-visit-maldives-spc.cnn"], "Source": ["cnn"], "Location": false, "ByLine": false, "Writers": [[]], "FirstPublishDate": ["2020-03-16T06:42:51Z"], "LastModifiedDate": ["2020-03-16T06:42:51Z"], "Headline": ["5 reasons to Insta love Maldives"], "Section": ["travel"], "MappedSection": ["TRAVEL"], "Article_Body": ["Looking for tranquility, peace, pristine beaches, water sports and fantastic cuisine? Maldives ticks all those boxes -- and many more.  "], "Language": false}