{"Type": ["video"], "Url": ["https://www.cnn.com/videos/business/2020/01/09/megyn-kelly-bombshell-reaction-orig.cnn-business"], "Source": ["cnn"], "Location": false, "ByLine": false, "Writers": [[]], "FirstPublishDate": ["2020-01-09T19:58:10Z"], "LastModifiedDate": ["2020-01-09T20:34:22Z"], "Headline": ["Megyn Kelly tears up watching 'Bombshell'"], "Section": ["business"], "MappedSection": ["BUSINESS"], "Article_Body": ["Megyn Kelly has shared her reaction to the film \"Bombshell,\" which depicts Roger Ailes' downfall at Fox News. Charlize Theron portrays Kelly in the film."], "Language": false}