{"Type": ["video"], "Url": ["https://www.cnn.com/videos/entertainment/2020/04/25/davido-dolce--gabanna-song-proceeds-relief-efforts-vpx.cnn"], "Source": ["cnn"], "Location": [null], "ByLine": [null], "Writers": [[]], "FirstPublishDate": ["2020-04-25T17:43:14Z"], "LastModifiedDate": ["2020-04-25T17:45:52Z"], "Headline": ["Davido donating proceeds of music video to coronavirus relief"], "Section": ["entertainment"], "MappedSection": ["ENTERTAINMENT"], "Article_Body": ["CNN's Chloe Melas speaks to Nigerian music star Davido about his pledge to donate proceeds from his new music video from the song \"Dolce & Gabanna\" to coronavirus relief efforts.  "], "Language": false}