{"Type": ["video"], "Url": ["https://www.cnn.com/videos/entertainment/2020/04/17/leann-rimes-intv-meditation-music-mxp-vpx.hln"], "Source": ["cnn"], "Location": false, "ByLine": false, "Writers": [[]], "FirstPublishDate": ["2020-04-17T15:03:37Z"], "LastModifiedDate": ["2020-04-17T15:03:37Z"], "Headline": ["LeAnn Rimes wants to help fans with music and meditation"], "Section": ["entertainment"], "MappedSection": ["ENTERTAINMENT"], "Article_Body": ["Singer LeAnn Rimes spoke to CNN's Chloe Melas about how she is trying to help her fans cope with the Covid-19 pandemic through music and meditation."], "Language": false}